setup.cfg
setup.py
./__init__.py
./country.py
./country.xml
./tryton.cfg
./tests/__init__.py
./tests/test_country.py
./tests/test_views_depends.py
./view/country_form.xml
openlabs_country_sequence.egg-info/PKG-INFO
openlabs_country_sequence.egg-info/SOURCES.txt
openlabs_country_sequence.egg-info/dependency_links.txt
openlabs_country_sequence.egg-info/entry_points.txt
openlabs_country_sequence.egg-info/not-zip-safe
openlabs_country_sequence.egg-info/requires.txt
openlabs_country_sequence.egg-info/top_level.txt