Metadata-Version: 1.1
Name: openlabs-country-sequence
Version: 3.4.0.1
Summary: This module adds sequence field to country module
Home-page: http://www.openlabs.co.in/
Author: Openlabs Technologies and Consulting (P) Ltd.
Author-email: info@openlabs.co.in
License: GPL-3
Platform: UNKNOWN
Classifier: Development Status :: 4 - Beta
Classifier: Environment :: Plugins
Classifier: Intended Audience :: Developers
Classifier: License :: OSI Approved :: GNU General Public License v3 (GPLv3)
Classifier: Natural Language :: English
Classifier: Operating System :: OS Independent
Classifier: Programming Language :: Python
Classifier: Framework :: Tryton
Classifier: Topic :: Office/Business
